pdfmarker/__init__.py
pdfmarker/colors.py
pdfmarker/pdfmarker.py
pdfmarker-0.2.0.dist-info/LICENSE
pdfmarker-0.2.0.dist-info/METADATA
pdfmarker-0.2.0.dist-info/WHEEL
pdfmarker-0.2.0.dist-info/RECORD
