Metadata-Version: 2.1
Name: pdfmarker
Version: 0.2.0
Summary: Simple tool to mark/add highlights to pdf documents.
Home-page: https://github.com/TomUijtdehaag/pdfmarker
License: GNU General Public License v3.0
Author: Tom Uijtdehaag
Author-email: tjl.udh@gmail.com
Requires-Python: >=3.8.1,<4.0.0
Classifier: License :: Other/Proprietary License
Classifier: Programming Language :: Python :: 3
Classifier: Programming Language :: Python :: 3.9
Classifier: Programming Language :: Python :: 3.10
Classifier: Programming Language :: Python :: 3.11
Classifier: Programming Language :: Python :: 3.12
Requires-Dist: PyMuPDF (>=1.24.0,<2.0.0)
